<annotation><filename>271.jpg</filename><size>
		<width>500</width>
		<height>500</height>
		<depth>3</depth>
	</size>
<object><name>psylla</name>
				<bndbox>
					<xmin>230</xmin>
					<ymin>102</ymin>
					<xmax>259</xmax>
					<ymax>163</ymax>
				</bndbox>
			</object><object><name>psylla</name>
				<bndbox>
					<xmin>173</xmin>
					<ymin>143</ymin>
					<xmax>200</xmax>
					<ymax>183</ymax>
				</bndbox>
			</object><object><name>psylla</name>
				<bndbox>
					<xmin>289</xmin>
					<ymin>256</ymin>
					<xmax>323</xmax>
					<ymax>295</ymax>
				</bndbox>
			</object><object><name>psylla</name>
				<bndbox>
					<xmin>246</xmin>
					<ymin>219</ymin>
					<xmax>264</xmax>
					<ymax>253</ymax>
				</bndbox>
			</object><object><name>psylla</name>
				<bndbox>
					<xmin>249</xmin>
					<ymin>420</ymin>
					<xmax>278</xmax>
					<ymax>443</ymax>
				</bndbox>
			</object></annotation>